zsl_jwt/__init__.py
zsl_jwt/codec.py
zsl_jwt/configuration.py
zsl_jwt/decorators.py
zsl_jwt/module.py
zsl_jwt/auth/__init__.py
zsl_jwt/auth/configuration.py
zsl_jwt/auth/controller.py
zsl_jwt/auth/module.py
zsl_jwt/auth/service.py
zsl_jwt-1.0.2.dist-info/AUTHORS.rst
zsl_jwt-1.0.2.dist-info/LICENSE
zsl_jwt-1.0.2.dist-info/METADATA
zsl_jwt-1.0.2.dist-info/WHEEL
zsl_jwt-1.0.2.dist-info/top_level.txt
zsl_jwt-1.0.2.dist-info/RECORD
