Metadata-Version: 2.1
Name: zsl_jwt
Version: 1.0.2
Summary: A JWT implementation for ZSL
Author-email: Martin Babka <babka@atteq.com>, "Atteq s.r.o." <open.source@atteq.com>
License: Copyright (c) 2017, Martin Babka
Classifier: Development Status :: 5 - Production/Stable
Classifier: Intended Audience :: Developers
Classifier: License :: OSI Approved :: BSD License
Classifier: Operating System :: Unix
Classifier: Operating System :: POSIX
Classifier: Operating System :: Microsoft :: Windows
Classifier: Programming Language :: Python
Classifier: Programming Language :: Python :: 3
Classifier: Programming Language :: Python :: 3.12
Classifier: Topic :: Utilities
Requires-Python: >=3.12
License-File: LICENSE
License-File: AUTHORS.rst
Requires-Dist: zsl>=0.16.5
Requires-Dist: Jinja2
Requires-Dist: PyYAML
Requires-Dist: future
Requires-Dist: pyjwt
Provides-Extra: report
Requires-Dist: docutils; extra == "report"
Requires-Dist: readme-renderer; extra == "report"
Requires-Dist: pygments; extra == "report"
Provides-Extra: dev
Requires-Dist: build; extra == "dev"
Requires-Dist: check-manifest; extra == "dev"
Requires-Dist: coverage; extra == "dev"
Requires-Dist: Flake8-pyproject; extra == "dev"
Requires-Dist: flake8; extra == "dev"
Requires-Dist: isort; extra == "dev"
Requires-Dist: pytest-cov; extra == "dev"
Requires-Dist: pytest; extra == "dev"
